grpc_orchestrator/__init__.py
grpc_orchestrator/saga_pb2.py
grpc_orchestrator/saga_pb2_grpc.py
grpc_orchestrator/service_base.py
grpc_orchestrator/core/models.py
grpc_orchestrator/core/orchestrator.py
grpc_orchestrator/core/client/client.py
grpc_orchestrator/core/connection/grpc_connection.py
grpc_orchestrator/core/connection/manager.py
grpc_orchestrator/core/services/__init__.py
grpc_orchestrator/core/services/example_services/service.py
grpc_orchestrator/core/storage/base.py
grpc_orchestrator/core/storage/memory.py
grpc_orchestrator/core/storage/postgres.py
grpc_orchestrator/utils/pretty.py
grpc_orchestrator-0.0.6.dist-info/licenses/LICENSE.txt
grpc_orchestrator-0.0.6.dist-info/METADATA
grpc_orchestrator-0.0.6.dist-info/WHEEL
grpc_orchestrator-0.0.6.dist-info/top_level.txt
grpc_orchestrator-0.0.6.dist-info/RECORD
