Metadata-Version: 2.4
Name: grpc_orchestrator
Version: 0.0.6
Summary: A gRPC-based Saga Orchestration System for distributed transactions
Home-page: https://github.com/bunrongGithub/grpc_orchestrator/tree/backup/simple_python_sdk
Author: Ron Saroeun
Author-email: ronsaroeun668@gmail.com
Keywords: grpc,grpc orchestrator,grpc microservices,distributed transactions,python grpc,saga pattern,grpc saga,transaction orchestrator,python microservices
Classifier: Programming Language :: Python :: 3
Classifier: License :: OSI Approved :: MIT License
Classifier: Operating System :: OS Independent
Classifier: Development Status :: 4 - Beta
Classifier: Intended Audience :: Developers
Classifier: Topic :: Software Development :: Libraries
Classifier: Topic :: System :: Distributed Computing
Classifier: Framework :: AsyncIO
Requires-Python: >=3.7
License-File: LICENSE.txt
Requires-Dist: grpcio>=1.56
Requires-Dist: protobuf>=4.21
Dynamic: author
Dynamic: author-email
Dynamic: classifier
Dynamic: description
Dynamic: description-content-type
Dynamic: home-page
Dynamic: keywords
Dynamic: license-file
Dynamic: requires-dist
Dynamic: requires-python
Dynamic: summary
